nexia/__init__.py
nexia/automation.py
nexia/const.py
nexia/home.py
nexia/roomiq.py
nexia/sensor.py
nexia/thermostat.py
nexia/util.py
nexia/zone.py
nexia-2.11.1.dist-info/licenses/AUTHORS.rst
nexia-2.11.1.dist-info/licenses/LICENSE
nexia-2.11.1.dist-info/METADATA
nexia-2.11.1.dist-info/WHEEL
nexia-2.11.1.dist-info/top_level.txt
nexia-2.11.1.dist-info/RECORD
