Metadata-Version: 2.4
Name: nexia
Version: 2.11.1
Summary: Python library for connecting to nexia
Author-email: "J. Nick Koston" <nick@koston.org>
License: Apache-2.0
Project-URL: Homepage, https://github.com/bdraco/nexia
Keywords: nexia
Classifier: Development Status :: 2 - Pre-Alpha
Classifier: Intended Audience :: Developers
Classifier: License :: OSI Approved :: Apache Software License
Classifier: Natural Language :: English
Classifier: Programming Language :: Python :: 3
Classifier: Programming Language :: Python :: 3.9
Classifier: Programming Language :: Python :: 3.10
Requires-Python: >=3.9
License-File: LICENSE
License-File: AUTHORS.rst
Requires-Dist: aiohttp
Requires-Dist: orjson
Requires-Dist: propcache
Dynamic: license-file
